bernhard_cletus/__init__.py
bernhard_cletus/pb.py
bernhard_cletus-0.2.6.dist-info/DESCRIPTION.rst
bernhard_cletus-0.2.6.dist-info/METADATA
bernhard_cletus-0.2.6.dist-info/metadata.json
bernhard_cletus-0.2.6.dist-info/RECORD
bernhard_cletus-0.2.6.dist-info/top_level.txt
bernhard_cletus-0.2.6.dist-info/WHEEL
