Metadata-Version: 2.0
Name: bernhard-cletus
Version: 0.2.6
Summary: Python client for Riemann to test sending metrics with double instead of float. Do not use!
Home-page: UNKNOWN
Author: Cletus
Author-email: Helljunkz@gmail.com
License: UNKNOWN
Platform: UNKNOWN
Classifier: Development Status :: 4 - Beta
Classifier: Environment :: Other Environment
Classifier: Intended Audience :: Developers
Classifier: License :: OSI Approved :: Apache Software License
Classifier: Operating System :: MacOS :: MacOS X
Classifier: Operating System :: POSIX
Classifier: Operating System :: Unix
Classifier: Programming Language :: Python
Classifier: Programming Language :: Python :: 2
Classifier: Programming Language :: Python :: 3
Classifier: Topic :: Internet :: Log Analysis
Classifier: Topic :: Utilities
Classifier: Topic :: System :: Networking :: Monitoring
Requires-Dist: protobuf (>=2.4)
